myscelium/__init__.py
myscelium/core.py
myscelium-0.0.dev0.dist-info/entry_points.txt
myscelium-0.0.dev0.dist-info/LICENSE.md
myscelium-0.0.dev0.dist-info/METADATA
myscelium-0.0.dev0.dist-info/WHEEL
myscelium-0.0.dev0.dist-info/RECORD
