Metadata-Version: 2.3
Name: myscelium
Version: 0.0.dev0
Summary: A modern, advanced framework.
License: Proprietary
Author: Cristian Camargo
Author-email: ccf@cdone.com.br
Requires-Python: >=3.10,<4.0
Classifier: License :: Other/Proprietary License
Classifier: Programming Language :: Python :: 3
Classifier: Programming Language :: Python :: 3.10
Classifier: Programming Language :: Python :: 3.11
Classifier: Programming Language :: Python :: 3.12
Classifier: Programming Language :: Python :: 3.13
Requires-Dist: pandas (>=2.2.2,<3.0.0)
Requires-Dist: toml (>=0.10.2,<0.11.0)
Project-URL: Documentation, https://github.com/letalboy/myscelium#readme
Project-URL: Homepage, https://github.com/letalboy/myscelium
Project-URL: Repository, https://github.com/letalboy/myscelium
